odoo9_addon_database_cleanup-9.0.1.0.0.99.dev53-py3.8-nspkg.pth
odoo_addons/database_cleanup/README.rst
odoo_addons/database_cleanup/__init__.py
odoo_addons/database_cleanup/__openerp__.py
odoo_addons/database_cleanup/identifier_adapter.py
odoo_addons/database_cleanup/i18n/am.po
odoo_addons/database_cleanup/i18n/ar.po
odoo_addons/database_cleanup/i18n/bg.po
odoo_addons/database_cleanup/i18n/bs.po
odoo_addons/database_cleanup/i18n/ca.po
odoo_addons/database_cleanup/i18n/ca_ES.po
odoo_addons/database_cleanup/i18n/cs.po
odoo_addons/database_cleanup/i18n/da.po
odoo_addons/database_cleanup/i18n/da_DK.po
odoo_addons/database_cleanup/i18n/database_cleanup.pot
odoo_addons/database_cleanup/i18n/de.po
odoo_addons/database_cleanup/i18n/el_GR.po
odoo_addons/database_cleanup/i18n/en_GB.po
odoo_addons/database_cleanup/i18n/es.po
odoo_addons/database_cleanup/i18n/es_AR.po
odoo_addons/database_cleanup/i18n/es_CL.po
odoo_addons/database_cleanup/i18n/es_CO.po
odoo_addons/database_cleanup/i18n/es_CR.po
odoo_addons/database_cleanup/i18n/es_DO.po
odoo_addons/database_cleanup/i18n/es_EC.po
odoo_addons/database_cleanup/i18n/es_ES.po
odoo_addons/database_cleanup/i18n/es_MX.po
odoo_addons/database_cleanup/i18n/es_PE.po
odoo_addons/database_cleanup/i18n/es_PY.po
odoo_addons/database_cleanup/i18n/es_VE.po
odoo_addons/database_cleanup/i18n/et.po
odoo_addons/database_cleanup/i18n/eu.po
odoo_addons/database_cleanup/i18n/fa.po
odoo_addons/database_cleanup/i18n/fi.po
odoo_addons/database_cleanup/i18n/fr.po
odoo_addons/database_cleanup/i18n/fr_CA.po
odoo_addons/database_cleanup/i18n/fr_CH.po
odoo_addons/database_cleanup/i18n/gl.po
odoo_addons/database_cleanup/i18n/gl_ES.po
odoo_addons/database_cleanup/i18n/he.po
odoo_addons/database_cleanup/i18n/hr.po
odoo_addons/database_cleanup/i18n/hr_HR.po
odoo_addons/database_cleanup/i18n/hu.po
odoo_addons/database_cleanup/i18n/id.po
odoo_addons/database_cleanup/i18n/it.po
odoo_addons/database_cleanup/i18n/ja.po
odoo_addons/database_cleanup/i18n/ko.po
odoo9_addon_database_cleanup-9.0.1.0.0.99.dev53.dist-info/METADATA
odoo9_addon_database_cleanup-9.0.1.0.0.99.dev53.dist-info/WHEEL
odoo9_addon_database_cleanup-9.0.1.0.0.99.dev53.dist-info/namespace_packages.txt
odoo9_addon_database_cleanup-9.0.1.0.0.99.dev53.dist-info/top_level.txt
odoo9_addon_database_cleanup-9.0.1.0.0.99.dev53.dist-info/RECORD
